{"artifacts":[{"id":"48de8c8713bc1537","name":"HAMS_ifort_Win","version":"UNKNOWN","type":"binary","foundBy":"pe-binary-package-cataloger","locations":[{"path":"/SourceCode/HAMS_ifort_Win.exe","accessPath":"/SourceCode/HAMS_ifort_Win.exe","annotations":{"evidence":"primary"}}],"licenses":[],"language":"","cpes":[{"cpe":"cpe:2.3:a:HAMS-ifort-Win:HAMS-ifort-Win:*:*:*:*:*:*:*:*","source":"syft-generated"},{"cpe":"cpe:2.3:a:HAMS-ifort-Win:HAMS_ifort_Win:*:*:*:*:*:*:*:*","source":"syft-generated"},{"cpe":"cpe:2.3:a:HAMS_ifort_Win:HAMS-ifort-Win:*:*:*:*:*:*:*:*","source":"syft-generated"},{"cpe":"cpe:2.3:a:HAMS_ifort_Win:HAMS_ifort_Win:*:*:*:*:*:*:*:*","source":"syft-generated"},{"cpe":"cpe:2.3:a:HAMS-ifort:HAMS-ifort-Win:*:*:*:*:*:*:*:*","source":"syft-generated"},{"cpe":"cpe:2.3:a:HAMS-ifort:HAMS_ifort_Win:*:*:*:*:*:*:*:*","source":"syft-generated"},{"cpe":"cpe:2.3:a:HAMS_ifort:HAMS-ifort-Win:*:*:*:*:*:*:*:*","source":"syft-generated"},{"cpe":"cpe:2.3:a:HAMS_ifort:HAMS_ifort_Win:*:*:*:*:*:*:*:*","source":"syft-generated"},{"cpe":"cpe:2.3:a:HAMS:HAMS-ifort-Win:*:*:*:*:*:*:*:*","source":"syft-generated"},{"cpe":"cpe:2.3:a:HAMS:HAMS_ifort_Win:*:*:*:*:*:*:*:*","source":"syft-generated"}],"purl":"","metadataType":"pe-binary","metadata":{"VersionResources":null}},{"id":"1840fdcde16ed70d","name":"HAMS_x64","version":"UNKNOWN","type":"binary","foundBy":"pe-binary-package-cataloger","locations":[{"path":"/Bin/HAMS_x64.exe","accessPath":"/Bin/HAMS_x64.exe","annotations":{"evidence":"primary"}}],"licenses":[],"language":"","cpes":[{"cpe":"cpe:2.3:a:HAMS-x64:HAMS-x64:*:*:*:*:*:*:*:*","source":"syft-generated"},{"cpe":"cpe:2.3:a:HAMS-x64:HAMS_x64:*:*:*:*:*:*:*:*","source":"syft-generated"},{"cpe":"cpe:2.3:a:HAMS_x64:HAMS-x64:*:*:*:*:*:*:*:*","source":"syft-generated"},{"cpe":"cpe:2.3:a:HAMS_x64:HAMS_x64:*:*:*:*:*:*:*:*","source":"syft-generated"},{"cpe":"cpe:2.3:a:HAMS-x64:HAMS-x:*:*:*:*:*:*:*:*","source":"syft-generated"},{"cpe":"cpe:2.3:a:HAMS-x64:HAMS_x:*:*:*:*:*:*:*:*","source":"syft-generated"},{"cpe":"cpe:2.3:a:HAMS-x:HAMS-x64:*:*:*:*:*:*:*:*","source":"syft-generated"},{"cpe":"cpe:2.3:a:HAMS-x:HAMS_x64:*:*:*:*:*:*:*:*","source":"syft-generated"},{"cpe":"cpe:2.3:a:HAMS_x64:HAMS-x:*:*:*:*:*:*:*:*","source":"syft-generated"},{"cpe":"cpe:2.3:a:HAMS_x64:HAMS_x:*:*:*:*:*:*:*:*","source":"syft-generated"},{"cpe":"cpe:2.3:a:HAMS_x:HAMS-x64:*:*:*:*:*:*:*:*","source":"syft-generated"},{"cpe":"cpe:2.3:a:HAMS_x:HAMS_x64:*:*:*:*:*:*:*:*","source":"syft-generated"},{"cpe":"cpe:2.3:a:HAMS-x:HAMS-x:*:*:*:*:*:*:*:*","source":"syft-generated"},{"cpe":"cpe:2.3:a:HAMS-x:HAMS_x:*:*:*:*:*:*:*:*","source":"syft-generated"},{"cpe":"cpe:2.3:a:HAMS:HAMS-x64:*:*:*:*:*:*:*:*","source":"syft-generated"},{"cpe":"cpe:2.3:a:HAMS:HAMS_x64:*:*:*:*:*:*:*:*","source":"syft-generated"},{"cpe":"cpe:2.3:a:HAMS_x:HAMS-x:*:*:*:*:*:*:*:*","source":"syft-generated"},{"cpe":"cpe:2.3:a:HAMS_x:HAMS_x:*:*:*:*:*:*:*:*","source":"syft-generated"},{"cpe":"cpe:2.3:a:HAMS:HAMS-x:*:*:*:*:*:*:*:*","source":"syft-generated"},{"cpe":"cpe:2.3:a:HAMS:HAMS_x:*:*:*:*:*:*:*:*","source":"syft-generated"}],"purl":"","metadataType":"pe-binary","metadata":{"VersionResources":null}},{"id":"e7e3ebc12f83b8a1","name":"Intel(R) OpenMP* Runtime Library","version":"5.0","type":"binary","foundBy":"pe-binary-package-cataloger","locations":[{"path":"/Bin/libiomp5md.dll","accessPath":"/Bin/libiomp5md.dll","annotations":{"evidence":"primary"}}],"licenses":[],"language":"","cpes":[],"purl":"","metadataType":"pe-binary","metadata":{"VersionResources":[{"key":"Comments","value":"Intel(R) OpenMP* Performance Library version 5.0.20160916 for Intel(R) 64 architecture built on 2016-09-16 21:43:23 UTC."},{"key":"CompanyName","value":"Intel Corporation"},{"key":"FileDescription","value":"Intel(R) OpenMP* Runtime Library"},{"key":"FileVersion","value":"20160916"},{"key":"InternalName","value":"libiomp5md.dll"},{"key":"LegalCopyright","value":"Copyright (C) 1997-2016, Intel Corporation. All rights reserved."},{"key":"OriginalFilename","value":"libiomp5md.dll"},{"key":"ProductName","value":"Intel(R) OpenMP* Runtime Library"},{"key":"ProductVersion","value":"5.0"}]}},{"id":"0e357da577364941","name":"Intel(R) OpenMP* Runtime Library","version":"5.0","type":"binary","foundBy":"pe-binary-package-cataloger","locations":[{"path":"/CertTest/Cylinder/libiomp5md.dll","accessPath":"/CertTest/Cylinder/libiomp5md.dll","annotations":{"evidence":"primary"}}],"licenses":[],"language":"","cpes":[],"purl":"","metadataType":"pe-binary","metadata":{"VersionResources":[{"key":"Comments","value":"Intel(R) OpenMP* Performance Library version 5.0.20160916 for Intel(R) 64 architecture built on 2016-09-16 21:43:23 UTC."},{"key":"CompanyName","value":"Intel Corporation"},{"key":"FileDescription","value":"Intel(R) OpenMP* Runtime Library"},{"key":"FileVersion","value":"20160916"},{"key":"InternalName","value":"libiomp5md.dll"},{"key":"LegalCopyright","value":"Copyright (C) 1997-2016, Intel Corporation. All rights reserved."},{"key":"OriginalFilename","value":"libiomp5md.dll"},{"key":"ProductName","value":"Intel(R) OpenMP* Runtime Library"},{"key":"ProductVersion","value":"5.0"}]}},{"id":"94e623bd856ed45d","name":"Intel(R) OpenMP* Runtime Library","version":"5.0","type":"binary","foundBy":"pe-binary-package-cataloger","locations":[{"path":"/CertTest/DeepCwind/libiomp5md.dll","accessPath":"/CertTest/DeepCwind/libiomp5md.dll","annotations":{"evidence":"primary"}}],"licenses":[],"language":"","cpes":[],"purl":"","metadataType":"pe-binary","metadata":{"VersionResources":[{"key":"Comments","value":"Intel(R) OpenMP* Performance Library version 5.0.20160916 for Intel(R) 64 architecture built on 2016-09-16 21:43:23 UTC."},{"key":"CompanyName","value":"Intel Corporation"},{"key":"FileDescription","value":"Intel(R) OpenMP* Runtime Library"},{"key":"FileVersion","value":"20160916"},{"key":"InternalName","value":"libiomp5md.dll"},{"key":"LegalCopyright","value":"Copyright (C) 1997-2016, Intel Corporation. All rights reserved."},{"key":"OriginalFilename","value":"libiomp5md.dll"},{"key":"ProductName","value":"Intel(R) OpenMP* Runtime Library"},{"key":"ProductVersion","value":"5.0"}]}},{"id":"7279083da76d9bd6","name":"Intel(R) OpenMP* Runtime Library","version":"5.0","type":"binary","foundBy":"pe-binary-package-cataloger","locations":[{"path":"/CertTest/HywindSpar/libiomp5md.dll","accessPath":"/CertTest/HywindSpar/libiomp5md.dll","annotations":{"evidence":"primary"}}],"licenses":[],"language":"","cpes":[],"purl":"","metadataType":"pe-binary","metadata":{"VersionResources":[{"key":"Comments","value":"Intel(R) OpenMP* Performance Library version 5.0.20160916 for Intel(R) 64 architecture built on 2016-09-16 21:43:23 UTC."},{"key":"CompanyName","value":"Intel Corporation"},{"key":"FileDescription","value":"Intel(R) OpenMP* Runtime Library"},{"key":"FileVersion","value":"20160916"},{"key":"InternalName","value":"libiomp5md.dll"},{"key":"LegalCopyright","value":"Copyright (C) 1997-2016, Intel Corporation. All rights reserved."},{"key":"OriginalFilename","value":"libiomp5md.dll"},{"key":"ProductName","value":"Intel(R) OpenMP* Runtime Library"},{"key":"ProductVersion","value":"5.0"}]}},{"id":"c290fb1fa1a726e8","name":"Intel(R) OpenMP* Runtime Library","version":"5.0","type":"binary","foundBy":"pe-binary-package-cataloger","locations":[{"path":"/CertTest/Moonpool/libiomp5md.dll","accessPath":"/CertTest/Moonpool/libiomp5md.dll","annotations":{"evidence":"primary"}}],"licenses":[],"language":"","cpes":[],"purl":"","metadataType":"pe-binary","metadata":{"VersionResources":[{"key":"Comments","value":"Intel(R) OpenMP* Performance Library version 5.0.20160916 for Intel(R) 64 architecture built on 2016-09-16 21:43:23 UTC."},{"key":"CompanyName","value":"Intel Corporation"},{"key":"FileDescription","value":"Intel(R) OpenMP* Runtime Library"},{"key":"FileVersion","value":"20160916"},{"key":"InternalName","value":"libiomp5md.dll"},{"key":"LegalCopyright","value":"Copyright (C) 1997-2016, Intel Corporation. All rights reserved."},{"key":"OriginalFilename","value":"libiomp5md.dll"},{"key":"ProductName","value":"Intel(R) OpenMP* Runtime Library"},{"key":"ProductVersion","value":"5.0"}]}},{"id":"aa7e1c0e1bc6c4c3","name":"WAMIT_MeshTran","version":"UNKNOWN","type":"binary","foundBy":"pe-binary-package-cataloger","locations":[{"path":"/MeshConverter/WAMIT_MeshTran.exe","accessPath":"/MeshConverter/WAMIT_MeshTran.exe","annotations":{"evidence":"primary"}}],"licenses":[],"language":"","cpes":[{"cpe":"cpe:2.3:a:WAMIT-MeshTran:WAMIT-MeshTran:*:*:*:*:*:*:*:*","source":"syft-generated"},{"cpe":"cpe:2.3:a:WAMIT-MeshTran:WAMIT_MeshTran:*:*:*:*:*:*:*:*","source":"syft-generated"},{"cpe":"cpe:2.3:a:WAMIT_MeshTran:WAMIT-MeshTran:*:*:*:*:*:*:*:*","source":"syft-generated"},{"cpe":"cpe:2.3:a:WAMIT_MeshTran:WAMIT_MeshTran:*:*:*:*:*:*:*:*","source":"syft-generated"},{"cpe":"cpe:2.3:a:WAMIT:WAMIT-MeshTran:*:*:*:*:*:*:*:*","source":"syft-generated"},{"cpe":"cpe:2.3:a:WAMIT:WAMIT_MeshTran:*:*:*:*:*:*:*:*","source":"syft-generated"}],"purl":"","metadataType":"pe-binary","metadata":{"VersionResources":null}},{"id":"8b0b47d65eba36e9","name":"actions/checkout","version":"v2","type":"github-action","foundBy":"github-actions-usage-cataloger","locations":[{"path":"/.github/workflows/gfortran-ci.yml","accessPath":"/.github/workflows/gfortran-ci.yml","annotations":{"evidence":"primary"}}],"licenses":[],"language":"","cpes":[{"cpe":"cpe:2.3:a:actions\\/checkout:actions\\/checkout:v2:*:*:*:*:*:*:*","source":"syft-generated"}],"purl":"pkg:github/actions/checkout@v2","metadataType":"github-actions-use-statement","metadata":{"value":"actions/checkout@v2"}},{"id":"7b1482daeacf57f0","name":"actions/setup-python","version":"v2","type":"github-action","foundBy":"github-actions-usage-cataloger","locations":[{"path":"/.github/workflows/gfortran-ci.yml","accessPath":"/.github/workflows/gfortran-ci.yml","annotations":{"evidence":"primary"}}],"licenses":[],"language":"","cpes":[{"cpe":"cpe:2.3:a:actions\\/setup-python:actions\\/setup-python:v2:*:*:*:*:*:*:*","source":"syft-generated"},{"cpe":"cpe:2.3:a:actions\\/setup-python:actions\\/setup_python:v2:*:*:*:*:*:*:*","source":"syft-generated"},{"cpe":"cpe:2.3:a:actions\\/setup_python:actions\\/setup-python:v2:*:*:*:*:*:*:*","source":"syft-generated"},{"cpe":"cpe:2.3:a:actions\\/setup_python:actions\\/setup_python:v2:*:*:*:*:*:*:*","source":"syft-generated"},{"cpe":"cpe:2.3:a:actions\\/setup:actions\\/setup-python:v2:*:*:*:*:*:*:*","source":"syft-generated"},{"cpe":"cpe:2.3:a:actions\\/setup:actions\\/setup_python:v2:*:*:*:*:*:*:*","source":"syft-generated"}],"purl":"pkg:github/actions/setup-python@v2","metadataType":"github-actions-use-statement","metadata":{"value":"actions/setup-python@v2"}}],"artifactRelationships":[{"parent":"0e357da577364941","child":"7c0ae95a8192f930","type":"evident-by","metadata":{"kind":"primary"}},{"parent":"1840fdcde16ed70d","child":"72ec94a23ae70c7c","type":"evident-by","metadata":{"kind":"primary"}},{"parent":"48de8c8713bc1537","child":"2364a2fe711be001","type":"evident-by","metadata":{"kind":"primary"}},{"parent":"7279083da76d9bd6","child":"b3c03cad74fcfdd0","type":"evident-by","metadata":{"kind":"primary"}},{"parent":"74a611bf9f06d8414dbc8ab37c7765b52f2d1f7ef7b5c03c55e0669839653b74","child":"0e357da577364941","type":"contains"},{"parent":"74a611bf9f06d8414dbc8ab37c7765b52f2d1f7ef7b5c03c55e0669839653b74","child":"1840fdcde16ed70d","type":"contains"},{"parent":"74a611bf9f06d8414dbc8ab37c7765b52f2d1f7ef7b5c03c55e0669839653b74","child":"48de8c8713bc1537","type":"contains"},{"parent":"74a611bf9f06d8414dbc8ab37c7765b52f2d1f7ef7b5c03c55e0669839653b74","child":"7279083da76d9bd6","type":"contains"},{"parent":"74a611bf9f06d8414dbc8ab37c7765b52f2d1f7ef7b5c03c55e0669839653b74","child":"7b1482daeacf57f0","type":"contains"},{"parent":"74a611bf9f06d8414dbc8ab37c7765b52f2d1f7ef7b5c03c55e0669839653b74","child":"8b0b47d65eba36e9","type":"contains"},{"parent":"74a611bf9f06d8414dbc8ab37c7765b52f2d1f7ef7b5c03c55e0669839653b74","child":"94e623bd856ed45d","type":"contains"},{"parent":"74a611bf9f06d8414dbc8ab37c7765b52f2d1f7ef7b5c03c55e0669839653b74","child":"aa7e1c0e1bc6c4c3","type":"contains"},{"parent":"74a611bf9f06d8414dbc8ab37c7765b52f2d1f7ef7b5c03c55e0669839653b74","child":"c290fb1fa1a726e8","type":"contains"},{"parent":"74a611bf9f06d8414dbc8ab37c7765b52f2d1f7ef7b5c03c55e0669839653b74","child":"e7e3ebc12f83b8a1","type":"contains"},{"parent":"7b1482daeacf57f0","child":"29b5906f8c0bf054","type":"evident-by","metadata":{"kind":"primary"}},{"parent":"8b0b47d65eba36e9","child":"29b5906f8c0bf054","type":"evident-by","metadata":{"kind":"primary"}},{"parent":"94e623bd856ed45d","child":"fe0d21b5d04820d9","type":"evident-by","metadata":{"kind":"primary"}},{"parent":"aa7e1c0e1bc6c4c3","child":"6b2fab6dbf374be2","type":"evident-by","metadata":{"kind":"primary"}},{"parent":"c290fb1fa1a726e8","child":"ce900c46205c4aff","type":"evident-by","metadata":{"kind":"primary"}},{"parent":"e7e3ebc12f83b8a1","child":"cf61bba79bb83111","type":"evident-by","metadata":{"kind":"primary"}}],"files":[{"id":"29b5906f8c0bf054","location":{"path":"/.github/workflows/gfortran-ci.yml"},"metadata":{"mode":644,"type":"RegularFile","userID":501,"groupID":20,"mimeType":"text/plain","size":3795},"digests":[{"algorithm":"sha1","value":"87e00e1ca3751d8594a9cfabc893a22ba9ad8e46"},{"algorithm":"sha256","value":"ede7fd596e227c9cbf34d34b6ce25eb84d3e3f8fcbd4b6d94d9789a922270f1a"}]},{"id":"72ec94a23ae70c7c","location":{"path":"/Bin/HAMS_x64.exe"},"metadata":{"mode":644,"type":"RegularFile","userID":501,"groupID":20,"mimeType":"application/vnd.microsoft.portable-executable","size":10156032},"digests":[{"algorithm":"sha1","value":"9ad23b2f25d5f4f2fd1498e93e1a5bf220b9268d"},{"algorithm":"sha256","value":"05dd7c15669348aa7a905e98681ad3cb84a07f718d1663ceb5efe7d5b87d4617"}],"executable":{"format":"pe","hasExports":false,"hasEntrypoint":false,"importedLibraries":[]}},{"id":"cf61bba79bb83111","location":{"path":"/Bin/libiomp5md.dll"},"metadata":{"mode":644,"type":"RegularFile","userID":501,"groupID":20,"mimeType":"application/vnd.microsoft.portable-executable","size":1377184},"digests":[{"algorithm":"sha1","value":"1afe332fb6ac9be78e0632cae3e52697b4fcc19d"},{"algorithm":"sha256","value":"9be147b5614a62a3ff8b867735357d27b7a74b180f17340273250f218b833958"}],"executable":{"format":"pe","hasExports":true,"hasEntrypoint":false,"importedLibraries":[]}},{"id":"7c0ae95a8192f930","location":{"path":"/CertTest/Cylinder/libiomp5md.dll"},"metadata":{"mode":644,"type":"RegularFile","userID":501,"groupID":20,"mimeType":"application/vnd.microsoft.portable-executable","size":1377184},"digests":[{"algorithm":"sha1","value":"1afe332fb6ac9be78e0632cae3e52697b4fcc19d"},{"algorithm":"sha256","value":"9be147b5614a62a3ff8b867735357d27b7a74b180f17340273250f218b833958"}],"executable":{"format":"pe","hasExports":true,"hasEntrypoint":false,"importedLibraries":[]}},{"id":"fe0d21b5d04820d9","location":{"path":"/CertTest/DeepCwind/libiomp5md.dll"},"metadata":{"mode":644,"type":"RegularFile","userID":501,"groupID":20,"mimeType":"application/vnd.microsoft.portable-executable","size":1377184},"digests":[{"algorithm":"sha1","value":"1afe332fb6ac9be78e0632cae3e52697b4fcc19d"},{"algorithm":"sha256","value":"9be147b5614a62a3ff8b867735357d27b7a74b180f17340273250f218b833958"}],"executable":{"format":"pe","hasExports":true,"hasEntrypoint":false,"importedLibraries":[]}},{"id":"b3c03cad74fcfdd0","location":{"path":"/CertTest/HywindSpar/libiomp5md.dll"},"metadata":{"mode":644,"type":"RegularFile","userID":501,"groupID":20,"mimeType":"application/vnd.microsoft.portable-executable","size":1377184},"digests":[{"algorithm":"sha1","value":"1afe332fb6ac9be78e0632cae3e52697b4fcc19d"},{"algorithm":"sha256","value":"9be147b5614a62a3ff8b867735357d27b7a74b180f17340273250f218b833958"}],"executable":{"format":"pe","hasExports":true,"hasEntrypoint":false,"importedLibraries":[]}},{"id":"ce900c46205c4aff","location":{"path":"/CertTest/Moonpool/libiomp5md.dll"},"metadata":{"mode":644,"type":"RegularFile","userID":501,"groupID":20,"mimeType":"application/vnd.microsoft.portable-executable","size":1377184},"digests":[{"algorithm":"sha1","value":"1afe332fb6ac9be78e0632cae3e52697b4fcc19d"},{"algorithm":"sha256","value":"9be147b5614a62a3ff8b867735357d27b7a74b180f17340273250f218b833958"}],"executable":{"format":"pe","hasExports":true,"hasEntrypoint":false,"importedLibraries":[]}},{"id":"6b2fab6dbf374be2","location":{"path":"/MeshConverter/WAMIT_MeshTran.exe"},"metadata":{"mode":644,"type":"RegularFile","userID":501,"groupID":20,"mimeType":"application/vnd.microsoft.portable-executable","size":2239488},"digests":[{"algorithm":"sha1","value":"62522da05b20755868067827f0d37a0a380df07b"},{"algorithm":"sha256","value":"69466856e36b51b0d94ebf57c45c03b76a0a7d357d8cdee210836dc79f1a70b1"}],"executable":{"format":"pe","hasExports":false,"hasEntrypoint":false,"importedLibraries":[]}},{"id":"2364a2fe711be001","location":{"path":"/SourceCode/HAMS_ifort_Win.exe"},"metadata":{"mode":644,"type":"RegularFile","userID":501,"groupID":20,"mimeType":"application/vnd.microsoft.portable-executable","size":10155520},"digests":[{"algorithm":"sha1","value":"d95f101a155339935f56a59465b632bcf3b8df1f"},{"algorithm":"sha256","value":"2373c2ee44bdaabca7639dd43edf3e8247c3656f1e5dc8c77aa14e9ae7801608"}],"executable":{"format":"pe","hasExports":false,"hasEntrypoint":false,"importedLibraries":[]}}],"source":{"id":"74a611bf9f06d8414dbc8ab37c7765b52f2d1f7ef7b5c03c55e0669839653b74","name":"/Users/tian/Develop.localized/2023-oss-in-energy-data/repos/hams","version":"","type":"directory","metadata":{"path":"/Users/tian/Develop.localized/2023-oss-in-energy-data/repos/hams"}},"distro":{},"descriptor":{"name":"syft","version":"1.36.0","configuration":{"catalogers":{"requested":{"default":["directory","file"]},"used":["alpm-db-cataloger","apk-db-cataloger","binary-classifier-cataloger","cargo-auditable-binary-cataloger","cocoapods-cataloger","conan-cataloger","conda-meta-cataloger","dart-pubspec-cataloger","dart-pubspec-lock-cataloger","deb-archive-cataloger","dotnet-deps-binary-cataloger","dotnet-packages-lock-cataloger","dpkg-db-cataloger","elf-binary-package-cataloger","elixir-mix-lock-cataloger","erlang-otp-application-cataloger","erlang-rebar-lock-cataloger","file-content-cataloger","file-digest-cataloger","file-executable-cataloger","file-metadata-cataloger","github-action-workflow-usage-cataloger","github-actions-usage-cataloger","go-module-binary-cataloger","go-module-file-cataloger","graalvm-native-image-cataloger","haskell-cataloger","homebrew-cataloger","java-archive-cataloger","java-gradle-lockfile-cataloger","java-jvm-cataloger","java-pom-cataloger","javascript-lock-cataloger","linux-kernel-cataloger","lua-rock-cataloger","nix-cataloger","opam-cataloger","pe-binary-package-cataloger","php-composer-lock-cataloger","php-interpreter-cataloger","php-pear-serialized-cataloger","portage-cataloger","python-installed-package-cataloger","python-package-cataloger","r-package-cataloger","rpm-archive-cataloger","rpm-db-cataloger","ruby-gemfile-cataloger","ruby-gemspec-cataloger","rust-cargo-lock-cataloger","snap-cataloger","swift-package-manager-cataloger","swipl-pack-cataloger","terraform-lock-cataloger","wordpress-plugins-cataloger"]},"data-generation":{"generate-cpes":true},"files":{"content":{"globs":null,"skip-files-above-size":0},"hashers":["sha-1","sha-256"],"selection":"owned-by-package"},"licenses":{"coverage":75,"include-content":"none"},"packages":{"binary":["python-binary","python-binary-lib","pypy-binary-lib","go-binary","julia-binary","helm","redis-binary","nodejs-binary","go-binary-hint","busybox-binary","util-linux-binary","haproxy-binary","perl-binary","php-composer-binary","httpd-binary","memcached-binary","traefik-binary","arangodb-binary","postgresql-binary","mysql-binary","mysql-binary","mysql-binary","xtrabackup-binary","mariadb-binary","rust-standard-library-linux","rust-standard-library-macos","ruby-binary","erlang-binary","erlang-alpine-binary","erlang-library","swipl-binary","dart-binary","haskell-ghc-binary","haskell-cabal-binary","haskell-stack-binary","consul-binary","hashicorp-vault-binary","nginx-binary","bash-binary","openssl-binary","gcc-binary","fluent-bit-binary","wordpress-cli-binary","curl-binary","lighttpd-binary","proftpd-binary","zstd-binary","xz-binary","gzip-binary","sqlcipher-binary","jq-binary","chrome-binary","ffmpeg-binary","ffmpeg-library","ffmpeg-library","java-binary","java-jdb-binary"],"dotnet":{"dep-packages-must-claim-dll":true,"dep-packages-must-have-dll":false,"propagate-dll-claims-to-parents":true,"relax-dll-claims-when-bundling-detected":true},"golang":{"local-mod-cache-dir":"/Users/tian/go/pkg/mod","local-vendor-dir":"","main-module-version":{"from-build-settings":true,"from-contents":false,"from-ld-flags":true},"proxies":["https://proxy.golang.org","direct"],"search-local-mod-cache-licenses":false,"search-local-vendor-licenses":false,"search-remote-licenses":false},"java-archive":{"include-indexed-archives":true,"include-unindexed-archives":false,"maven-base-url":"https://repo1.maven.org/maven2","maven-localrepository-dir":"/Users/tian/.m2/repository","max-parent-recursive-depth":0,"resolve-transitive-dependencies":false,"use-maven-localrepository":false,"use-network":false},"javascript":{"include-dev-dependencies":false,"npm-base-url":"https://registry.npmjs.org","search-remote-licenses":false},"linux-kernel":{"catalog-modules":true},"nix":{"capture-owned-files":false},"python":{"guess-unpinned-requirements":false}},"relationships":{"exclude-binary-packages-with-file-ownership-overlap":true,"package-file-ownership":true,"package-file-ownership-overlap":true},"search":{"scope":"squashed"}}},"schema":{"version":"16.0.41","url":"https://raw.githubusercontent.com/anchore/syft/main/schema/json/schema-16.0.41.json"}}
